MANIFEST.in
README.md
setup.py
src/baluhn.py
src/baluhn.egg-info/PKG-INFO
src/baluhn.egg-info/SOURCES.txt
src/baluhn.egg-info/dependency_links.txt
src/baluhn.egg-info/top_level.txt