Metadata-Version: 2.1
Name: baluhn
Version: 0.1.2
Summary: A base-agnostic implementation of the Luhn Algorithm for Python. Useful for generating and verifying check digits.
Home-page: http://github.com/benhodgson/baluhn
Author: Ben Hodgson
Author-email: ben@benhodgson.com
Maintainer: Four Digits
Maintainer-email: info@fourdigits.nl
License: Public Domain
Keywords: luhn,mod10,check digit,luhn mod N
Platform: UNKNOWN
Classifier: Programming Language :: Python
Classifier: Development Status :: 4 - Beta
Classifier: Intended Audience :: Developers
Classifier: License :: Public Domain
Classifier: Operating System :: OS Independent
Classifier: Topic :: Software Development :: Libraries :: Python Modules
